fds/__init__.py
fds/sdk/__init__.py
fds/sdk/FactSetDebtCapitalStructure/__init__.py
fds/sdk/FactSetDebtCapitalStructure/api_client.py
fds/sdk/FactSetDebtCapitalStructure/configuration.py
fds/sdk/FactSetDebtCapitalStructure/exceptions.py
fds/sdk/FactSetDebtCapitalStructure/model_utils.py
fds/sdk/FactSetDebtCapitalStructure/rest.py
fds/sdk/FactSetDebtCapitalStructure/api/__init__.py
fds/sdk/FactSetDebtCapitalStructure/api/reference_api.py
fds/sdk/FactSetDebtCapitalStructure/apis/__init__.py
fds/sdk/FactSetDebtCapitalStructure/model/__init__.py
fds/sdk/FactSetDebtCapitalStructure/model/detail.py
fds/sdk/FactSetDebtCapitalStructure/model/details_request.py
fds/sdk/FactSetDebtCapitalStructure/model/details_request_body.py
fds/sdk/FactSetDebtCapitalStructure/model/details_response.py
fds/sdk/FactSetDebtCapitalStructure/model/error_object.py
fds/sdk/FactSetDebtCapitalStructure/model/error_response.py
fds/sdk/FactSetDebtCapitalStructure/model/ids.py
fds/sdk/FactSetDebtCapitalStructure/model/interim_details_request.py
fds/sdk/FactSetDebtCapitalStructure/model/interim_details_request_body.py
fds/sdk/FactSetDebtCapitalStructure/model/periodicity.py
fds/sdk/FactSetDebtCapitalStructure/models/__init__.py
fds.sdk.FactSetDebtCapitalStructure-1.0.1.dist-info/LICENSE
fds.sdk.FactSetDebtCapitalStructure-1.0.1.dist-info/METADATA
fds.sdk.FactSetDebtCapitalStructure-1.0.1.dist-info/WHEEL
fds.sdk.FactSetDebtCapitalStructure-1.0.1.dist-info/top_level.txt
fds.sdk.FactSetDebtCapitalStructure-1.0.1.dist-info/RECORD
